[
  {
    "ts": "2026-04-12T14:23:59Z",
    "slug": "barcelona",
    "ok": true,
    "size": 5629,
    "lastUpdate": null,
    "runId": "24308838253",
    "elapsed": 0
  },
  {
    "ts": "2026-04-12T14:28:29Z",
    "slug": "barcelona",
    "ok": true,
    "size": 5625,
    "lastUpdate": null,
    "runId": "24308914357",
    "elapsed": 0
  },
  {
    "ts": "2026-04-12T14:29:10Z",
    "slug": "blankenfelde",
    "ok": true,
    "size": 5489,
    "lastUpdate": null,
    "runId": "24308914357",
    "elapsed": 0
  },
  {
    "ts": "2026-04-12T14:32:14Z",
    "slug": "barcelona",
    "ok": true,
    "size": 5635,
    "lastUpdate": null,
    "runId": "24308984742",
    "elapsed": 0
  },
  {
    "ts": "2026-04-12T14:34:46Z",
    "slug": "barcelona",
    "ok": true,
    "size": 5628,
    "lastUpdate": null,
    "runId": "24309031279",
    "elapsed": 0
  },
  {
    "ts": "2026-04-12T14:35:36Z",
    "slug": "blankenfelde",
    "ok": true,
    "size": 5489,
    "lastUpdate": null,
    "runId": "24309031279",
    "elapsed": 0
  },
  {
    "ts": "2026-04-12T14:36:53Z",
    "slug": "blankenfelde",
    "ok": true,
    "size": 5488,
    "lastUpdate": "16:36",
    "runId": "24309041690",
    "elapsed": 0
  },
  {
    "ts": "2026-04-12T14:39:31Z",
    "slug": "barcelona",
    "ok": true,
    "size": 5626,
    "lastUpdate": "16:39",
    "runId": "24309117713",
    "elapsed": 0
  },
  {
    "ts": "2026-04-12T14:40:18Z",
    "slug": "blankenfelde",
    "ok": true,
    "size": 5492,
    "lastUpdate": "16:40",
    "runId": "24309117713",
    "elapsed": 0
  },
  {
    "ts": "2026-04-12T15:21:41Z",
    "slug": "barcelona",
    "ok": true,
    "size": 5641,
    "lastUpdate": "17:21",
    "runId": "24309894789",
    "elapsed": 0
  },
  {
    "ts": "2026-04-12T15:22:30Z",
    "slug": "blankenfelde",
    "ok": true,
    "size": 5451,
    "lastUpdate": "17:22",
    "runId": "24309894789",
    "elapsed": 0
  },
  {
    "ts": "2026-04-12T15:57:19Z",
    "slug": "barcelona",
    "ok": true,
    "size": 5537,
    "lastUpdate": "17:57",
    "runId": "24310566676",
    "elapsed": 0
  },
  {
    "ts": "2026-04-12T15:57:55Z",
    "slug": "blankenfelde",
    "ok": true,
    "size": 5426,
    "lastUpdate": "17:57",
    "runId": "24310566676",
    "elapsed": 0
  },
  {
    "ts": "2026-04-12T17:27:20Z",
    "slug": "barcelona",
    "ok": true,
    "size": 5574,
    "lastUpdate": "19:27",
    "runId": "24312247827",
    "elapsed": 0
  },
  {
    "ts": "2026-04-12T17:28:01Z",
    "slug": "blankenfelde",
    "ok": true,
    "size": 5461,
    "lastUpdate": "19:27",
    "runId": "24312247827",
    "elapsed": 0
  },
  {
    "ts": "2026-04-12T18:02:40Z",
    "slug": "barcelona",
    "ok": true,
    "size": 5597,
    "lastUpdate": "20:02",
    "runId": "24312914168",
    "elapsed": 0
  },
  {
    "ts": "2026-04-12T18:03:22Z",
    "slug": "blankenfelde",
    "ok": true,
    "size": 5461,
    "lastUpdate": "20:03",
    "runId": "24312914168",
    "elapsed": 0
  },
  {
    "ts": "2026-04-12T19:07:24Z",
    "slug": "barcelona",
    "ok": true,
    "size": 5584,
    "lastUpdate": "21:07",
    "runId": "24314151776",
    "elapsed": 0
  },
  {
    "ts": "2026-04-12T19:08:04Z",
    "slug": "blankenfelde",
    "ok": true,
    "size": 5464,
    "lastUpdate": "21:08",
    "runId": "24314151776",
    "elapsed": 0
  },
  {
    "ts": "2026-04-12T19:51:28Z",
    "slug": "barcelona",
    "ok": true,
    "size": 5578,
    "lastUpdate": "21:51",
    "runId": "24314992350",
    "elapsed": 0
  },
  {
    "ts": "2026-04-12T19:52:16Z",
    "slug": "blankenfelde",
    "ok": true,
    "size": 5476,
    "lastUpdate": "21:52",
    "runId": "24314992350",
    "elapsed": 0
  },
  {
    "ts": "2026-04-12T20:25:41Z",
    "slug": "barcelona",
    "ok": true,
    "size": 5592,
    "lastUpdate": "22:25",
    "runId": "24315640645",
    "elapsed": 0
  },
  {
    "ts": "2026-04-12T20:26:22Z",
    "slug": "blankenfelde",
    "ok": true,
    "size": 5442,
    "lastUpdate": "22:26",
    "runId": "24315640645",
    "elapsed": 0
  },
  {
    "ts": "2026-04-12T21:02:11Z",
    "slug": "barcelona",
    "ok": true,
    "size": 5590,
    "lastUpdate": "23:02",
    "runId": "24316314084",
    "elapsed": 0
  },
  {
    "ts": "2026-04-12T21:02:48Z",
    "slug": "blankenfelde",
    "ok": true,
    "size": 5455,
    "lastUpdate": "23:02",
    "runId": "24316314084",
    "elapsed": 0
  },
  {
    "ts": "2026-04-12T21:50:23Z",
    "slug": "barcelona",
    "ok": true,
    "size": 5658,
    "lastUpdate": "23:50",
    "runId": "24317214923",
    "elapsed": 0
  },
  {
    "ts": "2026-04-12T21:50:59Z",
    "slug": "blankenfelde",
    "ok": true,
    "size": 5480,
    "lastUpdate": "23:50",
    "runId": "24317214923",
    "elapsed": 0
  },
  {
    "ts": "2026-04-12T22:24:24Z",
    "slug": "barcelona",
    "ok": true,
    "size": 5580,
    "lastUpdate": "24:24",
    "runId": "24317844500",
    "elapsed": 0
  }
]